easeon/__init__.py
easeon/__main__.py
easeon/core.py
easeon/logging_helper.py
easeon/paths.py
easeon/cli/__init__.py
easeon/cli/cli_manager.py
easeon/cli/cli_parser.py
easeon/core/__init__.py
easeon/core/easeon_installer.py
easeon/core/easeon_utils.py
easeon/core/file_handler.py
easeon/core/logger.py
easeon/core/package_installer.py
easeon/core/package_io.py
easeon/core/package_list_manager.py
easeon/core/package_manager.py
easeon/core/package_name.py
easeon/core/package_operations.py
easeon/core/package_validator.py
easeon/core/pypi_search.py
easeon/core/pypi_utils.py
easeon/core/python_lib_installer.py
easeon/core/utils.py
easeon/core/virtual_env_manager.py
easeon-0.0.3.dist-info/METADATA
easeon-0.0.3.dist-info/WHEEL
easeon-0.0.3.dist-info/entry_points.txt
easeon-0.0.3.dist-info/top_level.txt
easeon-0.0.3.dist-info/RECORD
