Metadata-Version: 2.4
Name: easeon
Version: 0.0.3
Summary: Python Package Management Utility for effortless package installation and virtual environment management.
Home-page: https://github.com/buHtiG20241217/Easeon
Author: Kiran Soorya R.S
Author-email: "Kiran Soorya R.S" <hemalathakiransoorya2099@gmail.com>
License: MIT
Project-URL: Homepage, https://github.com/buHtiG20241217/Easeon
Classifier: Programming Language :: Python :: 3
Classifier: License :: OSI Approved :: MIT License
Classifier: Operating System :: OS Independent
Requires-Python: >=3.8
